ankidoc/__init__.py
ankidoc/__main__.py
ankidoc/adoc.py
ankidoc/anki.py
ankidoc/cli.py
ankidoc/docgen.py
ankidoc/modes.py
ankidoc/notegen.py
ankidoc-0.2.0.data/data/share/man/man1/ankidoc.1
ankidoc-0.2.0.dist-info/LICENSE.md
ankidoc-0.2.0.dist-info/METADATA
ankidoc-0.2.0.dist-info/WHEEL
ankidoc-0.2.0.dist-info/entry_points.txt
ankidoc-0.2.0.dist-info/top_level.txt
ankidoc-0.2.0.dist-info/RECORD
