Metadata-Version: 2.2
Name: ankidoc
Version: 0.2.0
Summary: convert asciidoc notes to anki notes
Author-email: Timo Früh <dev@tifrueh.ch>
License: # GNU GENERAL PUBLIC LICENSE
Project-URL: Homepage, https://github.com/tifrueh/ankidoc/
License-File: LICENSE.md
